{
  "hashedPid": "8a5db0ad424efe4e09622cc4a876cc4c338558384752b483ff69dda4dca1ef04",
  "levelOfAssurance": "LEVEL_1",
  "matchId": "some-unknown-no-match-id",
  "matchingDataset": {
    "addresses": [
      {
        "fromDate": "2005-05-14T00:00:00.000Z",
        "lines": [],
        "verified": true
      }
    ],
    "dateOfBirth": {
      "value": "1980-05-24",
      "verified": true
    },
    "firstName": {
      "value": "Joe",
      "verified": true
    },
    "gender": {
      "value": "MALE",
      "verified": true
    },
    "middleNames": {
      "value": "Bob Rob",
      "verified": true
    },
    "surnames": [
      {
        "from": "2010-01-20T00:00:00.000Z",
        "value": "Dou",
        "verified": true
      }
    ]
  }
}